pretty/__init__.py
pretty/__version__.py
pretty_py3-0.2.4.post1.dist-info/METADATA
pretty_py3-0.2.4.post1.dist-info/RECORD
pretty_py3-0.2.4.post1.dist-info/WHEEL
pretty_py3-0.2.4.post1.dist-info/top_level.txt
