Metadata-Version: 2.1
Name: pretty-py3
Version: 0.2.4.post1
Summary: extensible pprint successor - python3 version
Home-page: https://github.com/mgrandi/pretty-py3
Author: Mark Grandi
Author-email: markgrandi@gmail.com
License: UNKNOWN
Platform: UNKNOWN
Classifier: Programming Language :: Python :: 3
Classifier: License :: OSI Approved :: BSD License
Classifier: Operating System :: OS Independent
